Box2D/Box2D.py
Box2D/_Box2D.cpython-37m-x86_64-linux-gnu.so
Box2D/__init__.py
Box2D/b2/__init__.py
box2d_py-2.3.7.dist-info/LICENSE
box2d_py-2.3.7.dist-info/METADATA
box2d_py-2.3.7.dist-info/WHEEL
box2d_py-2.3.7.dist-info/top_level.txt
box2d_py-2.3.7.dist-info/RECORD
